{
	"configurations" : 
	[
		{
			"directories" : 
			[
				{
					"build" : ".",
					"jsonFile" : "directory-.-f5ebdc15457944623624.json",
					"minimumCMakeVersion" : 
					{
						"string" : "3.24.0"
					},
					"projectIndex" : 0,
					"source" : ".",
					"targetIndexes" : 
					[
						0,
						1
					]
				}
			],
			"name" : "",
			"projects" : 
			[
				{
					"directoryIndexes" : 
					[
						0
					],
					"name" : "Simple1_default_project",
					"targetIndexes" : 
					[
						0,
						1
					]
				}
			],
			"targets" : 
			[
				{
					"directoryIndex" : 0,
					"id" : "Simple1_default_default_PIC_AS_assemble::@6890427a1f51a3e7e1df",
					"jsonFile" : "target-Simple1_default_default_PIC_AS_assemble-430aa8fc8bfdef83a62c.json",
					"name" : "Simple1_default_default_PIC_AS_assemble",
					"projectIndex" : 0
				},
				{
					"directoryIndex" : 0,
					"id" : "Simple1_default_image_Y8BtFlFE::@6890427a1f51a3e7e1df",
					"jsonFile" : "target-Simple1_default_image_Y8BtFlFE-eea7ec6c0db969f33285.json",
					"name" : "Simple1_default_image_Y8BtFlFE",
					"projectIndex" : 0
				}
			]
		}
	],
	"kind" : "codemodel",
	"paths" : 
	{
		"build" : "/Users/lucasertugrul/LocalRepos/Year 3 Physics/MicroprocessorsLab/_build/Simple1/default",
		"source" : "/Users/lucasertugrul/LocalRepos/Year 3 Physics/MicroprocessorsLab/cmake/Simple1/default"
	},
	"version" : 
	{
		"major" : 2,
		"minor" : 7
	}
}
